{
	"1": {
		"time": 2.9,
		"level": 1,
		"id": 1,
		"note_uid": "s040100"
	},
	"2": {
		"time": 8.11,
		"level": 1,
		"id": 2,
		"note_uid": "s040601"
	},
	"3": {
		"time": 9.049999999999999,
		"level": 1,
		"id": 3,
		"note_uid": "s040301"
	},
	"4": {
		"time": 9.989999999999997,
		"level": 1,
		"id": 4,
		"note_uid": "s040601"
	},
	"5": {
		"time": 10.929999999999998,
		"level": 1,
		"id": 5,
		"note_uid": "s040301"
	},
	"6": {
		"time": 11.859999999999998,
		"level": 1,
		"id": 6,
		"note_uid": "s040601"
	},
	"7": {
		"time": 12.799999999999995,
		"level": 1,
		"id": 7,
		"note_uid": "s000701"
	},
	"8": {
		"time": 13.269999999999998,
		"level": 1,
		"id": 8,
		"note_uid": "s040701"
	},
	"9": {
		"time": 13.739999999999997,
		"level": 1,
		"id": 9,
		"note_uid": "s040901"
	},
	"10": {
		"time": 13.969999999999995,
		"level": 1,
		"id": 10,
		"note_uid": "s040901"
	},
	"11": {
		"time": 14.439999999999998,
		"level": 1,
		"id": 11,
		"note_uid": "s040701"
	},
	"12": {
		"time": 14.679999999999998,
		"level": 1,
		"id": 12,
		"note_uid": "s040701"
	},
	"13": {
		"time": 14.909999999999997,
		"level": 1,
		"id": 13,
		"note_uid": "s040701"
	},
	"14": {
		"time": 15.139999999999995,
		"level": 1,
		"id": 14,
		"note_uid": "s000601"
	},
	"15": {
		"time": 15.609999999999998,
		"level": 1,
		"id": 15,
		"note_uid": "s040301"
	},
	"16": {
		"time": 16.080000000000002,
		"level": 1,
		"id": 16,
		"note_uid": "s040301"
	},
	"17": {
		"time": 16.55,
		"level": 1,
		"id": 17,
		"note_uid": "s040301"
	},
	"18": {
		"time": 17.02,
		"level": 1,
		"id": 18,
		"note_uid": "s000701"
	},
	"19": {
		"time": 17.490000000000002,
		"level": 1,
		"id": 19,
		"note_uid": "s000701"
	},
	"20": {
		"time": 17.96,
		"level": 1,
		"id": 20,
		"note_uid": "s040301"
	},
	"21": {
		"time": 18.43,
		"level": 1,
		"id": 21,
		"note_uid": "s040301"
	},
	"22": {
		"time": 18.89,
		"level": 1,
		"id": 22,
		"note_uid": "s040301"
	},
	"23": {
		"time": 19.36,
		"level": 1,
		"id": 23,
		"note_uid": "s040301"
	},
	"24": {
		"time": 19.83,
		"level": 1,
		"id": 24,
		"note_uid": "s000701"
	},
	"25": {
		"time": 20.3,
		"level": 1,
		"id": 25,
		"note_uid": "s000701"
	},
	"26": {
		"time": 20.77,
		"level": 1,
		"id": 26,
		"note_uid": "s040301"
	},
	"27": {
		"time": 21.24,
		"level": 1,
		"id": 27,
		"note_uid": "s000701"
	},
	"28": {
		"time": 21.71,
		"level": 1,
		"id": 28,
		"note_uid": "s040301"
	},
	"29": {
		"time": 22.18,
		"level": 1,
		"id": 29,
		"note_uid": "s040701"
	},
	"30": {
		"time": 22.41,
		"level": 1,
		"id": 30,
		"note_uid": "s040701"
	},
	"31": {
		"time": 22.64,
		"level": 1,
		"id": 31,
		"note_uid": "s040701"
	},
	"32": {
		"time": 23.11,
		"level": 1,
		"id": 32,
		"note_uid": "s000701"
	},
	"33": {
		"time": 23.58,
		"level": 1,
		"id": 33,
		"note_uid": "s040301"
	},
	"34": {
		"time": 24.05,
		"level": 1,
		"id": 34,
		"note_uid": "s000701"
	},
	"35": {
		"time": 24.52,
		"level": 1,
		"id": 35,
		"note_uid": "s040301"
	},
	"36": {
		"time": 24.99,
		"level": 1,
		"id": 36,
		"note_uid": "s040301"
	},
	"37": {
		"time": 25.46,
		"level": 1,
		"id": 37,
		"note_uid": "s040301"
	},
	"38": {
		"time": 25.93,
		"level": 1,
		"id": 38,
		"note_uid": "s000701"
	},
	"39": {
		"time": 26.39,
		"level": 1,
		"id": 39,
		"note_uid": "s040301"
	},
	"40": {
		"time": 26.86,
		"level": 1,
		"id": 40,
		"note_uid": "s040301"
	},
	"41": {
		"time": 27.33,
		"level": 1,
		"id": 41,
		"note_uid": "s040301"
	},
	"42": {
		"time": 27.8,
		"level": 1,
		"id": 42,
		"note_uid": "s000701"
	},
	"43": {
		"time": 28.27,
		"level": 1,
		"id": 43,
		"note_uid": "s040901"
	},
	"44": {
		"time": 28.5,
		"level": 1,
		"id": 44,
		"note_uid": "s040901"
	},
	"45": {
		"time": 28.74,
		"level": 1,
		"id": 45,
		"note_uid": "s040901"
	},
	"46": {
		"time": 28.97,
		"level": 1,
		"id": 46,
		"note_uid": "s040901"
	},
	"47": {
		"time": 29.21,
		"level": 1,
		"id": 47,
		"note_uid": "s040901"
	},
	"48": {
		"time": 29.44,
		"level": 1,
		"id": 48,
		"note_uid": "s040901"
	},
	"49": {
		"time": 29.68,
		"level": 1,
		"id": 49,
		"note_uid": "s040901"
	},
	"50": {
		"time": 29.91,
		"level": 1,
		"id": 50,
		"note_uid": "s040901"
	},
	"51": {
		"time": 30.14,
		"level": 1,
		"id": 51,
		"note_uid": "s000601"
	},
	"52": {
		"time": 30.61,
		"level": 1,
		"id": 52,
		"note_uid": "s000701"
	},
	"53": {
		"time": 31.08,
		"level": 1,
		"id": 53,
		"note_uid": "s000701"
	},
	"54": {
		"time": 31.55,
		"level": 1,
		"id": 54,
		"note_uid": "s040406"
	},
	"55": {
		"time": 31.78,
		"level": 1,
		"id": 55,
		"note_uid": "s040406"
	},
	"56": {
		"time": 32.019999999999996,
		"level": 1,
		"id": 56,
		"note_uid": "s040406"
	},
	"57": {
		"time": 32.489999999999995,
		"level": 1,
		"id": 57,
		"note_uid": "s000701"
	},
	"58": {
		"time": 32.96,
		"level": 1,
		"id": 58,
		"note_uid": "s000701"
	},
	"59": {
		"time": 33.43,
		"level": 1,
		"id": 59,
		"note_uid": "s040406"
	},
	"60": {
		"time": 33.66,
		"level": 1,
		"id": 60,
		"note_uid": "s040406"
	},
	"61": {
		"time": 33.89,
		"level": 1,
		"id": 61,
		"note_uid": "s040406"
	},
	"62": {
		"time": 34.36,
		"level": 1,
		"id": 62,
		"note_uid": "s040601"
	},
	"63": {
		"time": 34.83,
		"level": 1,
		"id": 63,
		"note_uid": "s040601"
	},
	"64": {
		"time": 35.3,
		"level": 1,
		"id": 64,
		"note_uid": "s000701"
	},
	"65": {
		"time": 35.529999999999994,
		"level": 1,
		"id": 65,
		"note_uid": "s040901"
	},
	"66": {
		"time": 35.769999999999996,
		"level": 1,
		"id": 66,
		"note_uid": "s040901"
	},
	"67": {
		"time": 36.239999999999995,
		"level": 1,
		"id": 67,
		"note_uid": "s040601"
	},
	"68": {
		"time": 36.71,
		"level": 1,
		"id": 68,
		"note_uid": "s040601"
	},
	"69": {
		"time": 37.18,
		"level": 1,
		"id": 69,
		"note_uid": "s000701"
	},
	"70": {
		"time": 37.41,
		"level": 1,
		"id": 70,
		"note_uid": "s040701"
	},
	"71": {
		"time": 37.64,
		"level": 1,
		"id": 71,
		"note_uid": "s040701"
	},
	"72": {
		"time": 37.879999999999995,
		"level": 1,
		"id": 72,
		"note_uid": "s040701"
	},
	"73": {
		"time": 38.11,
		"level": 1,
		"id": 73,
		"note_uid": "s040701"
	},
	"74": {
		"time": 38.58,
		"level": 1,
		"id": 74,
		"note_uid": "s000701"
	},
	"75": {
		"time": 39.05,
		"level": 1,
		"id": 75,
		"note_uid": "s000701"
	},
	"76": {
		"time": 39.52,
		"level": 1,
		"id": 76,
		"note_uid": "s040701"
	},
	"77": {
		"time": 39.75,
		"level": 1,
		"id": 77,
		"note_uid": "s040701"
	},
	"78": {
		"time": 39.989999999999995,
		"level": 1,
		"id": 78,
		"note_uid": "s040701"
	},
	"79": {
		"time": 40.46,
		"level": 1,
		"id": 79,
		"note_uid": "s040901"
	},
	"80": {
		"time": 40.69,
		"level": 1,
		"id": 80,
		"note_uid": "s040901"
	},
	"81": {
		"time": 40.93,
		"level": 1,
		"id": 81,
		"note_uid": "s040901"
	},
	"82": {
		"time": 41.39,
		"level": 1,
		"id": 82,
		"note_uid": "s040601"
	},
	"83": {
		"time": 41.86,
		"level": 1,
		"id": 83,
		"note_uid": "s000403"
	},
	"84": {
		"time": 42.33,
		"level": 1,
		"id": 84,
		"note_uid": "s040701"
	},
	"85": {
		"time": 42.57,
		"level": 1,
		"id": 85,
		"note_uid": "s040701"
	},
	"86": {
		"time": 42.8,
		"level": 1,
		"id": 86,
		"note_uid": "s000701"
	},
	"87": {
		"time": 43.029999999999994,
		"level": 1,
		"id": 87,
		"note_uid": "s000601"
	},
	"88": {
		"time": 47.97,
		"level": 1,
		"id": 88,
		"note_uid": "s040101"
	},
	"89": {
		"time": 51.65,
		"level": 1,
		"id": 89,
		"note_uid": "s040106"
	},
	"90": {
		"time": 52.64,
		"level": 1,
		"id": 90,
		"note_uid": "s040601"
	},
	"91": {
		"time": 53.11,
		"level": 1,
		"id": 91,
		"note_uid": "s040601"
	},
	"92": {
		"time": 53.58,
		"level": 1,
		"id": 92,
		"note_uid": "s040601"
	},
	"93": {
		"time": 54.05,
		"level": 1,
		"id": 93,
		"note_uid": "s041101"
	},
	"94": {
		"time": 54.279999999999994,
		"level": 1,
		"id": 94,
		"note_uid": "s041101"
	},
	"95": {
		"time": 54.52,
		"level": 1,
		"id": 95,
		"note_uid": "s041101"
	},
	"96": {
		"time": 54.989999999999995,
		"level": 1,
		"id": 96,
		"note_uid": "s040301"
	},
	"97": {
		"time": 55.46,
		"level": 1,
		"id": 97,
		"note_uid": "s040301"
	},
	"98": {
		"time": 55.93,
		"level": 1,
		"id": 98,
		"note_uid": "s040301"
	},
	"99": {
		"time": 56.39,
		"level": 1,
		"id": 99,
		"note_uid": "s040301"
	},
	"100": {
		"time": 56.86,
		"level": 1,
		"id": 100,
		"note_uid": "s041101"
	},
	"101": {
		"time": 57.099999999999994,
		"level": 1,
		"id": 101,
		"note_uid": "s041101"
	},
	"102": {
		"time": 57.33,
		"level": 1,
		"id": 102,
		"note_uid": "s041101"
	},
	"103": {
		"time": 57.8,
		"level": 1,
		"id": 103,
		"note_uid": "s041101"
	},
	"104": {
		"time": 58.029999999999994,
		"level": 1,
		"id": 104,
		"note_uid": "s041101"
	},
	"105": {
		"time": 58.27,
		"level": 1,
		"id": 105,
		"note_uid": "s041101"
	},
	"106": {
		"time": 58.739999999999995,
		"level": 1,
		"id": 106,
		"note_uid": "s040107"
	},
	"107": {
		"time": 59.62,
		"level": 1,
		"id": 107,
		"note_uid": "s000403"
	},
	"108": {
		"time": 60.14,
		"level": 1,
		"id": 108,
		"note_uid": "s040601"
	},
	"109": {
		"time": 60.61,
		"level": 1,
		"id": 109,
		"note_uid": "s000701"
	},
	"110": {
		"time": 60.849999999999994,
		"level": 1,
		"id": 110,
		"note_uid": "s000701"
	},
	"111": {
		"time": 61.08,
		"level": 1,
		"id": 111,
		"note_uid": "s040901"
	},
	"112": {
		"time": 61.32,
		"level": 1,
		"id": 112,
		"note_uid": "s040901"
	},
	"113": {
		"time": 61.55,
		"level": 1,
		"id": 113,
		"note_uid": "s040901"
	},
	"114": {
		"time": 61.779999999999994,
		"level": 1,
		"id": 114,
		"note_uid": "s040901"
	},
	"115": {
		"time": 62.25,
		"level": 1,
		"id": 115,
		"note_uid": "s040701"
	},
	"116": {
		"time": 62.489999999999995,
		"level": 1,
		"id": 116,
		"note_uid": "s040701"
	},
	"117": {
		"time": 62.72,
		"level": 1,
		"id": 117,
		"note_uid": "s040701"
	},
	"118": {
		"time": 62.96,
		"level": 1,
		"id": 118,
		"note_uid": "s040701"
	},
	"119": {
		"time": 63.43,
		"level": 1,
		"id": 119,
		"note_uid": "s000701"
	},
	"120": {
		"time": 63.88999999999999,
		"level": 1,
		"id": 120,
		"note_uid": "s040502"
	},
	"121": {
		"time": 64.25,
		"level": 1,
		"id": 121,
		"note_uid": "s040502"
	},
	"122": {
		"time": 64.60000000000001,
		"level": 1,
		"id": 122,
		"note_uid": "s040502"
	},
	"123": {
		"time": 65.07000000000001,
		"level": 1,
		"id": 123,
		"note_uid": "s040701"
	},
	"124": {
		"time": 65.30000000000001,
		"level": 1,
		"id": 124,
		"note_uid": "s040701"
	},
	"125": {
		"time": 65.53000000000002,
		"level": 1,
		"id": 125,
		"note_uid": "s040701"
	},
	"126": {
		"time": 65.77000000000002,
		"level": 1,
		"id": 126,
		"note_uid": "s040701"
	},
	"127": {
		"time": 66.24000000000002,
		"level": 1,
		"id": 127,
		"note_uid": "s040901"
	},
	"128": {
		"time": 66.47000000000001,
		"level": 1,
		"id": 128,
		"note_uid": "s040901"
	},
	"129": {
		"time": 66.71000000000002,
		"level": 1,
		"id": 129,
		"note_uid": "s040406"
	},
	"130": {
		"time": 66.94000000000001,
		"level": 1,
		"id": 130,
		"note_uid": "s040406"
	},
	"131": {
		"time": 67.18000000000002,
		"level": 1,
		"id": 131,
		"note_uid": "s040406"
	},
	"132": {
		"time": 67.41000000000003,
		"level": 1,
		"id": 132,
		"note_uid": "s040406"
	},
	"133": {
		"time": 67.64000000000001,
		"level": 1,
		"id": 133,
		"note_uid": "s040601"
	},
	"134": {
		"time": 68.00000000000001,
		"level": 1,
		"id": 134,
		"note_uid": "s040601"
	},
	"135": {
		"time": 68.35000000000002,
		"level": 1,
		"id": 135,
		"note_uid": "s040406"
	},
	"136": {
		"time": 68.58000000000001,
		"level": 1,
		"id": 136,
		"note_uid": "s040406"
	},
	"137": {
		"time": 68.82000000000002,
		"level": 1,
		"id": 137,
		"note_uid": "s040901"
	},
	"138": {
		"time": 69.05000000000003,
		"level": 1,
		"id": 138,
		"note_uid": "s000701"
	},
	"139": {
		"time": 69.28000000000002,
		"level": 1,
		"id": 139,
		"note_uid": "s040901"
	},
	"140": {
		"time": 69.52000000000002,
		"level": 1,
		"id": 140,
		"note_uid": "s040901"
	},
	"141": {
		"time": 69.75000000000001,
		"level": 1,
		"id": 141,
		"note_uid": "s000701"
	},
	"142": {
		"time": 69.99000000000002,
		"level": 1,
		"id": 142,
		"note_uid": "s040901"
	},
	"143": {
		"time": 70.22000000000001,
		"level": 1,
		"id": 143,
		"note_uid": "s000601"
	},
	"144": {
		"time": 75.14000000000001,
		"level": 1,
		"id": 144,
		"note_uid": "s040103"
	},
	"145": {
		"time": 78.89000000000001,
		"level": 1,
		"id": 145,
		"note_uid": "s040103"
	},
	"146": {
		"time": 82.64000000000001,
		"level": 1,
		"id": 146,
		"note_uid": "s040103"
	},
	"147": {
		"time": 86.39000000000001,
		"level": 1,
		"id": 147,
		"note_uid": "s040103"
	},
	"148": {
		"time": 88.50000000000001,
		"level": 1,
		"id": 148,
		"note_uid": "s040406"
	},
	"149": {
		"time": 88.74000000000001,
		"level": 1,
		"id": 149,
		"note_uid": "s040406"
	},
	"150": {
		"time": 88.97000000000001,
		"level": 1,
		"id": 150,
		"note_uid": "s040406"
	},
	"151": {
		"time": 89.21000000000002,
		"level": 1,
		"id": 151,
		"note_uid": "s040701"
	},
	"152": {
		"time": 89.44000000000001,
		"level": 1,
		"id": 152,
		"note_uid": "s040701"
	},
	"153": {
		"time": 89.68000000000002,
		"level": 1,
		"id": 153,
		"note_uid": "s040701"
	},
	"154": {
		"time": 89.91000000000003,
		"level": 1,
		"id": 154,
		"note_uid": "s040701"
	},
	"155": {
		"time": 90.14000000000001,
		"level": 1,
		"id": 155,
		"note_uid": "s000601"
	},
	"156": {
		"time": 90.61000000000001,
		"level": 1,
		"id": 156,
		"note_uid": "s040901"
	},
	"157": {
		"time": 90.85000000000002,
		"level": 1,
		"id": 157,
		"note_uid": "s040901"
	},
	"158": {
		"time": 91.08000000000001,
		"level": 1,
		"id": 158,
		"note_uid": "s000407"
	},
	"159": {
		"time": 91.55000000000003,
		"level": 1,
		"id": 159,
		"note_uid": "s040406"
	},
	"160": {
		"time": 91.78000000000002,
		"level": 1,
		"id": 160,
		"note_uid": "s040406"
	},
	"161": {
		"time": 92.25000000000001,
		"level": 1,
		"id": 161,
		"note_uid": "s040406"
	},
	"162": {
		"time": 92.49000000000001,
		"level": 1,
		"id": 162,
		"note_uid": "s040406"
	},
	"163": {
		"time": 92.96000000000002,
		"level": 1,
		"id": 163,
		"note_uid": "s000701"
	},
	"164": {
		"time": 93.43000000000002,
		"level": 1,
		"id": 164,
		"note_uid": "s000701"
	},
	"165": {
		"time": 93.89000000000001,
		"level": 1,
		"id": 165,
		"note_uid": "s040601"
	},
	"166": {
		"time": 94.36000000000001,
		"level": 1,
		"id": 166,
		"note_uid": "s040901"
	},
	"167": {
		"time": 94.60000000000002,
		"level": 1,
		"id": 167,
		"note_uid": "s040901"
	},
	"168": {
		"time": 94.83000000000001,
		"level": 1,
		"id": 168,
		"note_uid": "s040901"
	},
	"169": {
		"time": 95.30000000000003,
		"level": 1,
		"id": 169,
		"note_uid": "s040502"
	},
	"170": {
		"time": 95.53000000000002,
		"level": 1,
		"id": 170,
		"note_uid": "s040502"
	},
	"171": {
		"time": 96.00000000000001,
		"level": 1,
		"id": 171,
		"note_uid": "s040502"
	},
	"172": {
		"time": 96.24000000000001,
		"level": 1,
		"id": 172,
		"note_uid": "s040502"
	},
	"173": {
		"time": 96.71000000000002,
		"level": 1,
		"id": 173,
		"note_uid": "s000701"
	},
	"174": {
		"time": 97.18000000000002,
		"level": 1,
		"id": 174,
		"note_uid": "s000701"
	},
	"175": {
		"time": 97.64000000000001,
		"level": 1,
		"id": 175,
		"note_uid": "s040601"
	},
	"176": {
		"time": 98.11000000000001,
		"level": 1,
		"id": 176,
		"note_uid": "s040701"
	},
	"177": {
		"time": 98.35000000000002,
		"level": 1,
		"id": 177,
		"note_uid": "s040701"
	},
	"178": {
		"time": 98.58000000000001,
		"level": 1,
		"id": 178,
		"note_uid": "s040701"
	},
	"179": {
		"time": 99.05000000000003,
		"level": 1,
		"id": 179,
		"note_uid": "s040406"
	},
	"180": {
		"time": 99.28000000000002,
		"level": 1,
		"id": 180,
		"note_uid": "s040406"
	},
	"181": {
		"time": 99.75000000000001,
		"level": 1,
		"id": 181,
		"note_uid": "s040901"
	},
	"182": {
		"time": 99.99000000000001,
		"level": 1,
		"id": 182,
		"note_uid": "s040901"
	},
	"183": {
		"time": 100.22,
		"level": 1,
		"id": 183,
		"note_uid": "s000407"
	},
	"184": {
		"time": 100.69,
		"level": 1,
		"id": 184,
		"note_uid": "s040701"
	},
	"185": {
		"time": 100.93000000000002,
		"level": 1,
		"id": 185,
		"note_uid": "s040701"
	},
	"186": {
		"time": 101.16000000000004,
		"level": 1,
		"id": 186,
		"note_uid": "s040701"
	},
	"187": {
		"time": 101.39,
		"level": 1,
		"id": 187,
		"note_uid": "s040701"
	},
	"188": {
		"time": 101.86,
		"level": 1,
		"id": 188,
		"note_uid": "s040502"
	},
	"189": {
		"time": 102.10000000000002,
		"level": 1,
		"id": 189,
		"note_uid": "s040502"
	},
	"190": {
		"time": 102.57000000000002,
		"level": 1,
		"id": 190,
		"note_uid": "s040406"
	},
	"191": {
		"time": 102.80000000000004,
		"level": 1,
		"id": 191,
		"note_uid": "s040406"
	},
	"192": {
		"time": 103.27000000000002,
		"level": 1,
		"id": 192,
		"note_uid": "s000701"
	},
	"193": {
		"time": 103.74000000000002,
		"level": 1,
		"id": 193,
		"note_uid": "s000701"
	},
	"194": {
		"time": 104.21000000000002,
		"level": 1,
		"id": 194,
		"note_uid": "s000701"
	},
	"195": {
		"time": 104.68000000000002,
		"level": 1,
		"id": 195,
		"note_uid": "s000701"
	},
	"196": {
		"time": 105.14,
		"level": 1,
		"id": 196,
		"note_uid": "s040901"
	},
	"197": {
		"time": 105.38000000000002,
		"level": 1,
		"id": 197,
		"note_uid": "s040901"
	},
	"198": {
		"time": 105.61,
		"level": 1,
		"id": 198,
		"note_uid": "s040901"
	},
	"199": {
		"time": 105.85000000000002,
		"level": 1,
		"id": 199,
		"note_uid": "s040901"
	},
	"200": {
		"time": 106.08,
		"level": 1,
		"id": 200,
		"note_uid": "s040901"
	},
	"201": {
		"time": 106.32000000000002,
		"level": 1,
		"id": 201,
		"note_uid": "s040901"
	},
	"202": {
		"time": 106.55000000000004,
		"level": 1,
		"id": 202,
		"note_uid": "s040901"
	},
	"203": {
		"time": 106.78000000000002,
		"level": 1,
		"id": 203,
		"note_uid": "s040901"
	},
	"204": {
		"time": 107.02000000000002,
		"level": 1,
		"id": 204,
		"note_uid": "s000601"
	},
	"205": {
		"time": 108.43000000000002,
		"level": 1,
		"id": 205,
		"note_uid": "s040104"
	},
	"206": {
		"time": 110.30000000000004,
		"level": 1,
		"id": 206,
		"note_uid": "s041001"
	},
	"207": {
		"time": 110.53000000000002,
		"level": 1,
		"id": 207,
		"note_uid": "s041001"
	},
	"208": {
		"time": 110.77000000000002,
		"level": 1,
		"id": 208,
		"note_uid": "s041001"
	},
	"209": {
		"time": 111.24000000000002,
		"level": 1,
		"id": 209,
		"note_uid": "s000701"
	},
	"210": {
		"time": 111.71000000000002,
		"level": 1,
		"id": 210,
		"note_uid": "s000701"
	},
	"211": {
		"time": 112.18000000000002,
		"level": 1,
		"id": 211,
		"note_uid": "s040901"
	},
	"212": {
		"time": 112.41000000000004,
		"level": 1,
		"id": 212,
		"note_uid": "s040901"
	},
	"213": {
		"time": 112.64,
		"level": 1,
		"id": 213,
		"note_uid": "s040901"
	},
	"214": {
		"time": 112.88000000000002,
		"level": 1,
		"id": 214,
		"note_uid": "s041001"
	},
	"215": {
		"time": 113.11,
		"level": 1,
		"id": 215,
		"note_uid": "s041001"
	},
	"216": {
		"time": 113.35000000000002,
		"level": 1,
		"id": 216,
		"note_uid": "s041001"
	},
	"217": {
		"time": 113.58,
		"level": 1,
		"id": 217,
		"note_uid": "s041001"
	},
	"218": {
		"time": 113.82000000000002,
		"level": 1,
		"id": 218,
		"note_uid": "s041001"
	},
	"219": {
		"time": 114.05000000000004,
		"level": 1,
		"id": 219,
		"note_uid": "s041001"
	},
	"220": {
		"time": 114.28000000000002,
		"level": 1,
		"id": 220,
		"note_uid": "s041001"
	},
	"221": {
		"time": 114.52000000000002,
		"level": 1,
		"id": 221,
		"note_uid": "s041001"
	},
	"222": {
		"time": 114.99000000000002,
		"level": 1,
		"id": 222,
		"note_uid": "s040601"
	},
	"223": {
		"time": 115.46000000000002,
		"level": 1,
		"id": 223,
		"note_uid": "s040601"
	},
	"224": {
		"time": 115.93000000000002,
		"level": 1,
		"id": 224,
		"note_uid": "s041001"
	},
	"225": {
		"time": 116.16000000000004,
		"level": 1,
		"id": 225,
		"note_uid": "s041001"
	},
	"226": {
		"time": 116.39,
		"level": 1,
		"id": 226,
		"note_uid": "s041001"
	},
	"227": {
		"time": 116.86,
		"level": 1,
		"id": 227,
		"note_uid": "s040601"
	},
	"228": {
		"time": 117.33,
		"level": 1,
		"id": 228,
		"note_uid": "s040301"
	},
	"229": {
		"time": 117.80000000000004,
		"level": 1,
		"id": 229,
		"note_uid": "s040601"
	},
	"230": {
		"time": 118.27000000000002,
		"level": 1,
		"id": 230,
		"note_uid": "s040301"
	},
	"231": {
		"time": 119.62000000000002,
		"level": 1,
		"id": 231,
		"note_uid": "s040105"
	},
	"232": {
		"time": 121.08,
		"level": 1,
		"id": 232,
		"note_uid": "s040106"
	},
	"233": {
		"time": 122.02000000000002,
		"level": 1,
		"id": 233,
		"note_uid": "s040701"
	},
	"234": {
		"time": 122.49000000000002,
		"level": 1,
		"id": 234,
		"note_uid": "s040701"
	},
	"235": {
		"time": 122.96000000000002,
		"level": 1,
		"id": 235,
		"note_uid": "s040701"
	},
	"236": {
		"time": 123.43000000000002,
		"level": 1,
		"id": 236,
		"note_uid": "s041101"
	},
	"237": {
		"time": 123.66000000000004,
		"level": 1,
		"id": 237,
		"note_uid": "s041101"
	},
	"238": {
		"time": 123.89,
		"level": 1,
		"id": 238,
		"note_uid": "s041101"
	},
	"239": {
		"time": 124.36,
		"level": 1,
		"id": 239,
		"note_uid": "s000701"
	},
	"240": {
		"time": 124.83,
		"level": 1,
		"id": 240,
		"note_uid": "s000701"
	},
	"241": {
		"time": 125.30000000000004,
		"level": 1,
		"id": 241,
		"note_uid": "s040301"
	},
	"242": {
		"time": 125.77000000000002,
		"level": 1,
		"id": 242,
		"note_uid": "s040301"
	},
	"243": {
		"time": 126.24000000000002,
		"level": 1,
		"id": 243,
		"note_uid": "s040301"
	},
	"244": {
		"time": 126.71000000000002,
		"level": 1,
		"id": 244,
		"note_uid": "s040301"
	},
	"245": {
		"time": 127.18000000000002,
		"level": 1,
		"id": 245,
		"note_uid": "s000701"
	},
	"246": {
		"time": 127.41000000000004,
		"level": 1,
		"id": 246,
		"note_uid": "s000701"
	},
	"247": {
		"time": 127.64,
		"level": 1,
		"id": 247,
		"note_uid": "s041101"
	},
	"248": {
		"time": 127.88,
		"level": 1,
		"id": 248,
		"note_uid": "s041101"
	},
	"249": {
		"time": 128.11,
		"level": 1,
		"id": 249,
		"note_uid": "s041101"
	},
	"250": {
		"time": 128.35,
		"level": 1,
		"id": 250,
		"note_uid": "s041101"
	},
	"251": {
		"time": 128.58,
		"level": 1,
		"id": 251,
		"note_uid": "s041101"
	},
	"252": {
		"time": 128.82,
		"level": 1,
		"id": 252,
		"note_uid": "s041101"
	},
	"253": {
		"time": 129.05,
		"level": 1,
		"id": 253,
		"note_uid": "s041101"
	},
	"254": {
		"time": 129.28,
		"level": 1,
		"id": 254,
		"note_uid": "s041101"
	},
	"255": {
		"time": 129.52,
		"level": 1,
		"id": 255,
		"note_uid": "s040601"
	},
	"256": {
		"time": 129.99,
		"level": 1,
		"id": 256,
		"note_uid": "s040601"
	},
	"257": {
		"time": 130.46,
		"level": 1,
		"id": 257,
		"note_uid": "s040601"
	},
	"258": {
		"time": 130.93,
		"level": 1,
		"id": 258,
		"note_uid": "s041101"
	},
	"259": {
		"time": 131.16,
		"level": 1,
		"id": 259,
		"note_uid": "s041101"
	},
	"260": {
		"time": 131.39,
		"level": 1,
		"id": 260,
		"note_uid": "s041101"
	},
	"261": {
		"time": 131.86,
		"level": 1,
		"id": 261,
		"note_uid": "s040601"
	},
	"262": {
		"time": 132.33,
		"level": 1,
		"id": 262,
		"note_uid": "s040301"
	},
	"263": {
		"time": 132.8,
		"level": 1,
		"id": 263,
		"note_uid": "s040601"
	},
	"264": {
		"time": 133.27,
		"level": 1,
		"id": 264,
		"note_uid": "s000701"
	},
	"265": {
		"time": 133.74,
		"level": 1,
		"id": 265,
		"note_uid": "s040601"
	},
	"266": {
		"time": 134.21,
		"level": 1,
		"id": 266,
		"note_uid": "s040301"
	},
	"267": {
		"time": 134.68,
		"level": 1,
		"id": 267,
		"note_uid": "s040406"
	},
	"268": {
		"time": 134.91,
		"level": 1,
		"id": 268,
		"note_uid": "s040406"
	},
	"269": {
		"time": 135.38,
		"level": 1,
		"id": 269,
		"note_uid": "s040406"
	},
	"270": {
		"time": 135.61,
		"level": 1,
		"id": 270,
		"note_uid": "s040406"
	},
	"271": {
		"time": 136.55,
		"level": 1,
		"id": 271,
		"note_uid": "s040107"
	},
	"272": {
		"time": 137.49,
		"level": 1,
		"id": 272,
		"note_uid": "s000701"
	},
	"273": {
		"time": 137.96,
		"level": 1,
		"id": 273,
		"note_uid": "s040301"
	},
	"274": {
		"time": 138.43,
		"level": 1,
		"id": 274,
		"note_uid": "s000701"
	},
	"275": {
		"time": 138.89,
		"level": 1,
		"id": 275,
		"note_uid": "s040301"
	},
	"276": {
		"time": 139.36,
		"level": 1,
		"id": 276,
		"note_uid": "s000701"
	},
	"277": {
		"time": 139.83,
		"level": 1,
		"id": 277,
		"note_uid": "s040301"
	},
	"278": {
		"time": 140.3,
		"level": 1,
		"id": 278,
		"note_uid": "s000701"
	},
	"279": {
		"time": 140.77,
		"level": 1,
		"id": 279,
		"note_uid": "s040301"
	},
	"280": {
		"time": 141.24,
		"level": 1,
		"id": 280,
		"note_uid": "s000701"
	},
	"281": {
		"time": 141.71,
		"level": 1,
		"id": 281,
		"note_uid": "s040301"
	},
	"282": {
		"time": 142.18,
		"level": 1,
		"id": 282,
		"note_uid": "s040202"
	},
	"283": {
		"time": 143.11,
		"level": 1,
		"id": 283,
		"note_uid": "s040202"
	},
	"284": {
		"time": 144.05,
		"level": 1,
		"id": 284,
		"note_uid": "s040202"
	},
	"285": {
		"time": 146.86,
		"level": 1,
		"id": 285,
		"note_uid": "s040102"
	}
}