{
	"1": {
		"cover": "stage/stage_1/stage_1",
		"scene": "game_scenes/scene_03/_prefab/scene_03",
		"music": "stage/stage_0/tutorial_music_2",
		"unlock": 0,
		"volume": 0.3,
		"difficulty": 1,
		"id": 1,
		"author": "unkown",
		"all_combo": 0,
		"name": "Tutorial",
		"all_star": 0,
		"event_id": 10,
		"note_json": "tutorial_new",
		"boss_note": 0,
		"all_perfect": 0
	},
	"2": {
		"cover": "stage/stage_1/stage_1",
		"scene": "game_scenes/scene_05/_prefab/scene_05",
		"music": "stage/stage_1/stoc_cheerful_promo_andreano",
		"unlock": 0,
		"volume": 0.7,
		"difficulty": 2,
		"id": 2,
		"author": "unkown",
		"all_combo": 104,
		"name": "Cheerful",
		"all_star": 7,
		"event_id": 0,
		"note_json": "cheerful",
		"boss_note": 0,
		"all_perfect": 104
	},
	"3": {
		"cover": "stage/stage_2/stage_2",
		"scene": "game_scenes/scene_05/_prefab/scene_05",
		"music": "stage/stage_2/dov_shall_we_meet_matsu",
		"unlock": 0,
		"volume": 0.7,
		"difficulty": 3,
		"id": 3,
		"author": "unkown",
		"all_combo": 92,
		"name": "Shall we meet",
		"all_star": 9,
		"event_id": 0,
		"note_json": "shall_we_meet",
		"boss_note": 0,
		"all_perfect": 92
	},
	"4": {
		"cover": "stage/stage_3/stage_3",
		"scene": "game_scenes/scene_05/_prefab/scene_05",
		"music": "stage/stage_3/stoc_survivin_reznik",
		"unlock": 0,
		"volume": 0.5,
		"difficulty": 4,
		"id": 4,
		"author": "Reznik",
		"all_combo": 154,
		"name": "Surviving",
		"all_star": 4,
		"event_id": 0,
		"note_json": "surviving",
		"boss_note": 0,
		"all_perfect": 154
	},
	"5": {
		"cover": "stage/stage_4/stage_4",
		"scene": "game_scenes/scene_05/_prefab/scene_05",
		"music": "stage/stage_4/pops_up_the_mind_wings",
		"unlock": 3,
		"volume": 0.4,
		"difficulty": 5,
		"id": 5,
		"author": "MusMus",
		"all_combo": 112,
		"name": "Pops up the mind wings",
		"all_star": 4,
		"event_id": 0,
		"note_json": "pops_up_the_mind_wings",
		"boss_note": 0,
		"all_perfect": 112
	},
	"6": {
		"cover": "stage/stage_5/stage_5",
		"scene": "game_scenes/scene_05/_prefab/scene_05",
		"music": "stage/stage_5/oke_song_15_raintable",
		"unlock": 6,
		"volume": 0.7,
		"difficulty": 6,
		"id": 6,
		"author": "魔王魂",
		"all_combo": 200,
		"name": "RainTable",
		"all_star": 4,
		"event_id": 0,
		"note_json": "raintable",
		"boss_note": "note/s05/0501/0501",
		"all_perfect": 200
	},
	"7": {
		"cover": "stage/stage_6/stage_6",
		"scene": "game_scenes/scene_03/_prefab/scene_03",
		"music": "stage/stage_6/funtastic_ft03_an_unfortunate_incident",
		"unlock": 9,
		"volume": 0.3,
		"difficulty": 7,
		"id": 7,
		"author": "Simons",
		"all_combo": 89,
		"name": "An Unfortunate Incident",
		"all_star": 7,
		"event_id": 0,
		"note_json": "an_unfortunate_incident",
		"boss_note": 0,
		"all_perfect": 89
	},
	"8": {
		"cover": "stage/stage_7/stage_7",
		"scene": "game_scenes/scene_03/_prefab/scene_03",
		"music": "stage/stage_7/wounderful_pain",
		"unlock": 12,
		"volume": 0.7,
		"difficulty": 8,
		"id": 8,
		"author": "Haloweak",
		"all_combo": 189,
		"name": "Wonderful Pain",
		"all_star": 4,
		"event_id": 1,
		"note_json": "wounderful_pain",
		"boss_note": 0,
		"all_perfect": 189
	},
	"9": {
		"cover": "stage/stage_9/stage_9",
		"scene": "game_scenes/scene_03/_prefab/scene_03",
		"music": "stage/stage_v1/music/amacha",
		"unlock": 18,
		"volume": 0.3,
		"difficulty": 9,
		"id": 9,
		"author": "Amacha",
		"all_combo": 210,
		"name": "真夜中のおもちゃ箱",
		"all_star": 4,
		"event_id": 1,
		"note_json": "amacha",
		"boss_note": 0,
		"all_perfect": 210
	},
	"10": {
		"cover": "stage/stage_10/stage_10",
		"scene": "game_scenes/scene_03/_prefab/scene_03",
		"music": "stage/stage_10/evolution",
		"unlock": 21,
		"volume": 0.8,
		"difficulty": 10,
		"id": 10,
		"author": "unkown",
		"all_combo": 250,
		"name": "Evolution",
		"all_star": 7,
		"event_id": 1,
		"note_json": "evolution",
		"boss_note": 0,
		"all_perfect": 250
	},
	"11": {
		"cover": "stage/stage_11/stage_11",
		"scene": "game_scenes/scene_03/_prefab/scene_03",
		"music": "stage/stage_11/greed",
		"unlock": 24,
		"volume": 0.4,
		"difficulty": 11,
		"id": 11,
		"author": "music-note.jp",
		"all_combo": 173,
		"name": "Greed",
		"all_star": 19,
		"event_id": 1,
		"note_json": "greed",
		"boss_note": 0,
		"all_perfect": 173
	},
	"12": {
		"cover": "stage/stage_12/stage_12",
		"scene": "game_scenes/scene_03/_prefab/scene_03",
		"music": "stage/stage_12/bgm_maoudamashii_cyber16",
		"unlock": 27,
		"volume": 0.7,
		"difficulty": 12,
		"id": 12,
		"author": "魔王魂",
		"all_combo": 117,
		"name": "サイバー16",
		"all_star": 4,
		"event_id": 1,
		"note_json": "bgm_maoudamashii_cyber16",
		"boss_note": 0,
		"all_perfect": 117
	},
	"13": {
		"cover": "stage/stage_13/stage_13",
		"scene": "game_scenes/scene_03/_prefab/scene_03",
		"music": "stage/stage_13/bgm_maoudamashii_cyber12",
		"unlock": 33,
		"volume": 0.7,
		"difficulty": 13,
		"id": 13,
		"author": "魔王魂",
		"all_combo": 214,
		"name": "サイバー12",
		"all_star": 4,
		"event_id": 11,
		"note_json": "bgm_maoudamashii_cyber12",
		"boss_note": "note/s03/0301/0301",
		"all_perfect": 214
	},
	"14": {
		"cover": "stage/stage_14/stage_14",
		"scene": "game_scenes/scene_03/_prefab/scene_03",
		"music": "stage/stage_14/oke_song_14_delvge",
		"unlock": 36,
		"volume": 0.7,
		"difficulty": 14,
		"id": 14,
		"author": "魔王魂",
		"all_combo": 325,
		"name": "Delvge",
		"all_star": 4,
		"event_id": 1,
		"note_json": "delvge",
		"boss_note": 0,
		"all_perfect": 325
	},
	"15": {
		"cover": "stage/stage_15/stage_15",
		"scene": "game_scenes/scene_03/_prefab/scene_03",
		"music": "stage/stage_15/confession",
		"unlock": 39,
		"volume": 0.7,
		"difficulty": 15,
		"id": 15,
		"author": "Haloweak",
		"all_combo": 270,
		"name": "Confession",
		"all_star": 4,
		"event_id": 1,
		"note_json": "confession",
		"boss_note": 0,
		"all_perfect": 270
	},
	"16": {
		"cover": "stage/stage_16/stage_16",
		"scene": "game_scenes/scene_04/_prefab/scene_04",
		"music": "stage/stage_v1/music/dov_stream_kyaai",
		"unlock": 42,
		"volume": 0.6,
		"difficulty": 16,
		"id": 16,
		"author": "kyaai",
		"all_combo": 280,
		"name": "Stream",
		"all_star": 4,
		"event_id": 1,
		"note_json": "stream",
		"boss_note": "note/s04/0401/0401",
		"all_perfect": 280
	},
	"17": {
		"cover": "stage/stage_old/stage_18",
		"scene": "game_scenes/scene_01/_prefab/scene_01",
		"music": "stage/stage_test/telekinesis",
		"unlock": 46,
		"volume": 0.6,
		"difficulty": 17,
		"id": 17,
		"author": "VS",
		"all_combo": 309,
		"name": "Telekinesis",
		"all_star": 30,
		"event_id": 1,
		"note_json": "telekinesis",
		"boss_note": 0,
		"all_perfect": 309
	},
	"18": {
		"cover": "stage/stage_test/stage_27",
		"scene": "game_scenes/scene_03/_prefab/scene_03",
		"music": "stage/stage_old/monkey_song",
		"unlock": 48,
		"volume": 0.6,
		"difficulty": 18,
		"id": 18,
		"author": "unkown",
		"all_combo": 200,
		"name": "MonkeySong",
		"all_star": 4,
		"event_id": 1,
		"note_json": "monkey_song",
		"boss_note": 0,
		"all_perfect": 200
	},
	"19": {
		"cover": "stage/stage_old/stage_28",
		"scene": "game_scenes/scene_03/_prefab/scene_03",
		"music": "stage/stage_old/lets_dance_boys",
		"unlock": 54,
		"volume": 0.6,
		"difficulty": 19,
		"id": 19,
		"author": "unkown",
		"all_combo": 200,
		"name": "LetsDanceBoys",
		"all_star": 4,
		"event_id": 1,
		"note_json": "lets_dance_boys",
		"boss_note": "note/s03/0301/0301",
		"all_perfect": 200
	},
	"20": {
		"cover": "stage/stage_old/stage_29",
		"scene": "game_scenes/scene_03/_prefab/scene_03",
		"music": "stage/stage_old/cindellera_song",
		"unlock": 60,
		"volume": 0.6,
		"difficulty": 20,
		"id": 20,
		"author": "unkown",
		"all_combo": 200,
		"name": "CindelleraSong",
		"all_star": 4,
		"event_id": 1,
		"note_json": "cindellera_song",
		"boss_note": "note/s03/0301/0301",
		"all_perfect": 200
	},
	"21": {
		"cover": "stage/stage_old/stage_30",
		"scene": "game_scenes/scene_03/_prefab/scene_03",
		"music": "stage/stage_old/lucky_love",
		"unlock": 65,
		"volume": 0.6,
		"difficulty": 21,
		"id": 21,
		"author": "unkown",
		"all_combo": 200,
		"name": "LuckyLove",
		"all_star": 4,
		"event_id": 1,
		"note_json": "lucky_love",
		"boss_note": "note/s03/0301/0301",
		"all_perfect": 200
	},
	"22": {
		"cover": "stage/stage_old/stage_31",
		"scene": "game_scenes/scene_03/_prefab/scene_03",
		"music": "stage/stage_old/masquerade",
		"unlock": 75,
		"volume": 0.6,
		"difficulty": 22,
		"id": 22,
		"author": "unkown",
		"all_combo": 200,
		"name": "Masquerade",
		"all_star": 4,
		"event_id": 1,
		"note_json": "masquerade",
		"boss_note": 0,
		"all_perfect": 200
	}
}